codedog/__init__.py
codedog/actors/__init__.py
codedog/actors/base.py
codedog/actors/reporters/__init__.py
codedog/actors/reporters/base.py
codedog/actors/reporters/code_review.py
codedog/actors/reporters/pr_summary.py
codedog/actors/reporters/pull_request.py
codedog/chains/__init__.py
codedog/chains/code_review/__init__.py
codedog/chains/code_review/base.py
codedog/chains/code_review/prompts.py
codedog/chains/code_review/translate_code_review_chain.py
codedog/chains/pr_summary/__init__.py
codedog/chains/pr_summary/base.py
codedog/chains/pr_summary/prompts.py
codedog/chains/pr_summary/translate_pr_summary_chain.py
codedog/chains/prompts.py
codedog/localization.py
codedog/models/__init__.py
codedog/models/blob.py
codedog/models/change_file.py
codedog/models/change_summary.py
codedog/models/code_review.py
codedog/models/commit.py
codedog/models/diff.py
codedog/models/issue.py
codedog/models/pr_summary.py
codedog/models/pull_request.py
codedog/models/repository.py
codedog/processors/__init__.py
codedog/processors/pull_request_processor.py
codedog/retrievers/__init__.py
codedog/retrievers/base.py
codedog/retrievers/github_retriever.py
codedog/retrievers/gitlab_retriever.py
codedog/templates/__init__.py
codedog/templates/grimoire_cn.py
codedog/templates/grimoire_en.py
codedog/templates/template_cn.py
codedog/templates/template_en.py
codedog/utils/__init__.py
codedog/utils/diff_utils.py
codedog/utils/langchain_utils.py
codedog/version.py
codedog-0.11.0.dist-info/LICENSE
codedog-0.11.0.dist-info/METADATA
codedog-0.11.0.dist-info/WHEEL
codedog-0.11.0.dist-info/entry_points.txt
codedog-0.11.0.dist-info/RECORD
