Metadata-Version: 2.1
Name: codedog
Version: 0.11.0
Summary: Codedog reviews your pull request using llm.
Home-page: https://www.codedog.ai
License: MIT
Keywords: code review,langchain,llm
Author: Arcadia
Author-email: arcadia822@gmail.com
Requires-Python: >=3.10,<3.11
Classifier: License :: OSI Approved :: MIT License
Classifier: Programming Language :: Python :: 3
Classifier: Programming Language :: Python :: 3.10
Requires-Dist: annotated-types (>=0.7.0,<0.8.0)
Requires-Dist: distro (>=1.9.0,<2.0.0)
Requires-Dist: h11 (>=0.14.0,<0.15.0)
Requires-Dist: langchain (>=0.2.11,<0.3.0)
Requires-Dist: langchain-community (>=0.2.10,<0.3.0)
Requires-Dist: langchain-openai (>=0.1.19,<0.2.0)
Requires-Dist: openai (>=1.37.1,<2.0.0)
Requires-Dist: pydantic (>=2.8.2,<3.0.0)
Requires-Dist: pydantic-core (>=2.20.1,<3.0.0)
Requires-Dist: pygithub (>=1.58.2,<3.0.0)
Requires-Dist: python-gitlab (>=3.14,<5.0)
Requires-Dist: unidiff (>=0.7.5,<0.8.0)
Project-URL: Bug Tracker, https://github.com/codedog-ai/codedog/issues
Project-URL: Discord, https://discord.gg/8TfqpFC4
Project-URL: Repository, https://www.github.com/codedog-ai/codedog
